{
	"sidebarBg":"#2e3440",
	"sidebarText":"#d8dee9",
	"sidebarUnreadText":"#eceff4",
	"sidebarTextHoverBg":"#4c566a",
	"sidebarTextActiveBorder":"#4c566a",
	"sidebarTextActiveColor":"#e5e9f0",
	"sidebarHeaderBg":"#4c566a",
	"sidebarHeaderTextColor":"#d8dee9",
	"onlineIndicator":"#a3be8c",
	"awayIndicator":"#EBCB8B",
	"dndIndicator":"#BF616A",
	"mentionBj":"#ebcb8b",
	"mentionColor":"#4c566a",
	"centerChannelBg":"#3b4252",
	"centerChannelColor":"#e5e9f0",
	"newMessageSeparator":"#ebcb8b",
	"linkColor":"#b48ead",
	"buttonBg":"#8fbcbb",
	"buttonColor":"#2e3440",
	"errorTextColor":"#fd5960",
	"mentionHighlightBg":"#ebcb8b",
	"mentionHighlightLink":"#4c566a",
	"codeTheme":"solarized-dark",
	"mentionBg":"#ebcb8b"
}
